vovk_hello_world/__init__.py
vovk_hello_world/api_client.py
vovk_hello_world/py.typed
vovk_hello_world/schema.json
vovk_hello_world-0.0.87.dist-info/METADATA
vovk_hello_world-0.0.87.dist-info/WHEEL
vovk_hello_world-0.0.87.dist-info/RECORD
