Metadata-Version: 2.4
Name: vovk_hello_world
Version: 0.0.87
Summary: A "Hello World!" app built with Next.js, Vovk.ts and Zod. For details, visit https://vovk.dev/hello-world
Project-URL: Homepage, https://vovk.dev/hello-world
Project-URL: Source, https://github.com/finom/vovk-hello-world.git
Project-URL: Issues, https://github.com/finom/vovk-hello-world/issues
Author: Andrey Gubanov
License: MIT
Keywords: api,openapi,vovk,zod
Requires-Python: >=3.8
Requires-Dist: jsonschema
Requires-Dist: requests
Requires-Dist: rfc3987
Requires-Dist: urllib3==1.26.15
Provides-Extra: dev
Requires-Dist: types-jsonschema; extra == 'dev'
Requires-Dist: types-requests; extra == 'dev'
